openioc2stix/__init__.py
openioc2stix/objectify.py
openioc2stix/openioc.py
openioc2stix/translate.py
openioc2stix/utils.py
openioc2stix/version.py
openioc2stix/xml.py
openioc2stix/tests/__init__.py
openioc2stix/tests/openioc_tests.py
openioc2stix/tests/utils_tests.py
openioc2stix/tests/xml_tests.py
openioc_to_stix-1.4.0.data/scripts/openioc-to-cybox.py
openioc_to_stix-1.4.0.data/scripts/openioc-to-stix.py
openioc_to_stix-1.4.0.dist-info/DESCRIPTION.rst
openioc_to_stix-1.4.0.dist-info/METADATA
openioc_to_stix-1.4.0.dist-info/RECORD
openioc_to_stix-1.4.0.dist-info/WHEEL
openioc_to_stix-1.4.0.dist-info/metadata.json
openioc_to_stix-1.4.0.dist-info/top_level.txt
