Metadata-Version: 2.0
Name: openioc-to-stix
Version: 1.4.0
Summary: Converts OpenIOC documents into STIX/CybOX documents.
Home-page: http://stix.mitre.org/
Author: The MITRE Corporation
Author-email: stix@mitre.org
License: BSD
Keywords: stix cybox openioc xml openioc-to-stix openioc-to-cybox
Platform: UNKNOWN
Classifier: Development Status :: 5 - Production/Stable
Classifier: Intended Audience :: Developers
Classifier: License :: OSI Approved :: BSD License
Classifier: Operating System :: OS Independent
Classifier: Programming Language :: Python :: 2
Classifier: Programming Language :: Python :: 2.6
Classifier: Programming Language :: Python :: 2.7
Classifier: Programming Language :: Python :: 3
Classifier: Programming Language :: Python :: 3.4
Classifier: Programming Language :: Python :: 3.5
Classifier: Programming Language :: Python :: 3.6
Requires-Dist: cybox (>=2.1.0.13)
Requires-Dist: lxml (>=3.3.5)
Requires-Dist: mixbox (>=1.0.1)
Requires-Dist: stix (>=1.2.0.2)
Requires-Dist: argparse; python_version == "2.6"
